baichat_py/__init__.py
baichat_py-0.3.0.dist-info/METADATA
baichat_py-0.3.0.dist-info/WHEEL
baichat_py-0.3.0.dist-info/RECORD
